hereby.py
hereby-0.3.1.data/scripts/hereby.py
hereby-0.3.1.dist-info/LICENSE
hereby-0.3.1.dist-info/METADATA
hereby-0.3.1.dist-info/WHEEL
hereby-0.3.1.dist-info/top_level.txt
hereby-0.3.1.dist-info/RECORD
